py_epic-0.1.19.dist-info/licenses/LICENSE
pyepic/__init__.py
pyepic/_types.py
pyepic/account.py
pyepic/auth.py
pyepic/errors.py
pyepic/http.py
pyepic/route.py
pyepic/xmpp.py
pyepic/fortnite/__init__.py
pyepic/fortnite/base.py
pyepic/fortnite/stw.py
pyepic/resources/__init__.py
pyepic/resources/lookup.py
pyepic/utils/__init__.py
pyepic/utils/dt.py
py_epic-0.1.19.dist-info/METADATA
py_epic-0.1.19.dist-info/WHEEL
py_epic-0.1.19.dist-info/top_level.txt
py_epic-0.1.19.dist-info/RECORD
