Metadata-Version: 2.4
Name: py-epic
Version: 0.1.19
Summary: HTTP wrapper for the Epic/Fortnite APIs.
Author-email: Delliott <dlelliott100@outlook.com>
Project-URL: Repository, https://github.com/delliott0000/PyEpic
Classifier: License :: OSI Approved :: MIT License
Classifier: Operating System :: OS Independent
Classifier: Development Status :: 3 - Alpha
Classifier: Intended Audience :: Developers
Classifier: Programming Language :: Python :: 3.10
Classifier: Programming Language :: Python :: 3.11
Classifier: Programming Language :: Python :: 3.12
Classifier: Programming Language :: Python :: 3.13
Requires-Python: >=3.10
License-File: LICENSE
Requires-Dist: aiohttp>=3.11.0
Dynamic: license-file
